{"pixiv_pic": [{"name": "109232755", "path": "./pixiv/2023-06-24-14-07-56/109232755.jpg", "index": 0, "user": "Werlosk", "ext": ".jpg"}, {"name": "109226104", "path": "./pixiv/2023-06-24-14-07-56/109226104.jpg", "index": 1, "user": "\u3061\u308d2\u767d\u91ce", "ext": ".jpg"}, {"name": "109261369", "path": "./pixiv/2023-06-24-14-07-56/109261369.jpg", "index": 2, "user": "\u89ba\u9192", "ext": ".jpg"}, {"name": "109239020", "path": "./pixiv/2023-06-24-14-07-56/109239020.jpg", "index": 3, "user": "\u3046\u3048\u306e\u307f\u304e", "ext": ".jpg"}, {"name": "109249018", "path": "./pixiv/2023-06-24-14-07-56/109249018.jpg", "index": 4, "user": "\u7d3a\u5c4b\u9d09\u6c5f", "ext": ".jpg"}, {"name": "109228961", "path": "./pixiv/2023-06-24-14-07-56/109228961.png", "index": 5, "user": "\u795e\u61763JINKEI", "ext": ".png"}, {"name": "109270529", "path": "./pixiv/2023-06-24-14-07-56/109270529.png", "index": 6, "user": "\u6d77\u3070\u305f\u308a", "ext": ".png"}, {"name": "109245457", "path": "./pixiv/2023-06-24-14-07-56/109245457.png", "index": 7, "user": "\u9069\u5f53\u7dd1", "ext": ".png"}, {"name": "109259770", "path": "./pixiv/2023-06-24-14-07-56/109259770.jpg", "index": 8, "user": "\u30dd\uff5e\u30f3\uff08\u51fa\u6c34\u307d\u3059\u304b\uff09", "ext": ".jpg"}, {"name": "109275847", "path": "./pixiv/2023-06-24-14-07-56/109275847.jpg", "index": 9, "user": "\u7d3a\u5c4b\u9d09\u6c5f", "ext": ".jpg"}, {"name": "109223494", "path": "./pixiv/2023-06-24-14-07-56/109223494.png", "index": 10, "user": "\u8d64\u5009", "ext": ".png"}, {"name": "109226474", "path": "./pixiv/2023-06-24-14-07-56/109226474.jpg", "index": 11, "user": "\u30df\u30c8\u26055117\u7f8a\u59eb\u6700\u7d42\u767a\u58f2", "ext": ".jpg"}, {"name": "109232737", "path": "./pixiv/2023-06-24-14-07-56/109232737.png", "index": 12, "user": "\u3048\u3093\u304e\u3088\u3057", "ext": ".png"}, {"name": "109235202", "path": "./pixiv/2023-06-24-14-07-56/109235202.jpg", "index": 13, "user": "\u72d7\u8138\u8138dogface", "ext": ".jpg"}, {"name": "109231246", "path": "./pixiv/2023-06-24-14-07-56/109231246.png", "index": 14, "user": "Hitsu", "ext": ".png"}, {"name": "109230420", "path": "./pixiv/2023-06-24-14-07-56/109230420.jpg", "index": 15, "user": "\u6f2b\u753b\u7d20\u6750\u5de5\u623f", "ext": ".jpg"}, {"name": "109228857", "path": "./pixiv/2023-06-24-14-07-56/109228857.png", "index": 16, "user": "\u3064\u306d@FANBOX\u59cb\u3081\u307e\u3057\u305f", "ext": ".png"}, {"name": "109223786", "path": "./pixiv/2023-06-24-14-07-56/109223786.jpg", "index": 17, "user": "\u4e0a\u5009\u30a8\u30af", "ext": ".jpg"}, {"name": "109270975", "path": "./pixiv/2023-06-24-14-07-56/109270975.jpg", "index": 18, "user": "\u30ce\u30fc\u30b3\u30d4\u30fc\u30e9\u30a4\u30c8\u30ac\u30fc\u30eb", "ext": ".jpg"}, {"name": "109238358", "path": "./pixiv/2023-06-24-14-07-56/109238358.png", "index": 19, "user": "\u6c34\u8996\u305a\u307f\ud83d\udc1f", "ext": ".png"}, {"name": "109245106", "path": "./pixiv/2023-06-24-14-07-56/109245106.jpg", "index": 20, "user": "\u304b\u3089\u306a\u304c\u308c", "ext": ".jpg"}, {"name": "109223589", "path": "./pixiv/2023-06-24-14-07-56/109223589.jpg", "index": 21, "user": "saraki\uff20\u304a\u4ed5\u4e8b\u52df\u96c6\u4e2d", "ext": ".jpg"}, {"name": "109268211", "path": "./pixiv/2023-06-24-14-07-56/109268211.png", "index": 22, "user": "risui@\u6625\u4f8b\u5927\u796d\u306f\u304a\u3084\u3059\u307f", "ext": ".png"}, {"name": "109260006", "path": "./pixiv/2023-06-24-14-07-56/109260006.jpg", "index": 23, "user": "\u7d2b\u96f2", "ext": ".jpg"}, {"name": "109264454", "path": "./pixiv/2023-06-24-14-07-56/109264454.png", "index": 24, "user": "\u5948\u5ddd\u30c8\u30e2", "ext": ".png"}, {"name": "109262740", "path": "./pixiv/2023-06-24-14-07-56/109262740.jpg", "index": 25, "user": "DIno", "ext": ".jpg"}, {"name": "109234534", "path": "./pixiv/2023-06-24-14-07-56/109234534.jpg", "index": 26, "user": "8810\uff5cHayato", "ext": ".jpg"}, {"name": "109238943", "path": "./pixiv/2023-06-24-14-07-56/109238943.jpg", "index": 27, "user": "azs_kn", "ext": ".jpg"}, {"name": "109223571", "path": "./pixiv/2023-06-24-14-07-56/109223571.png", "index": 28, "user": "GIN", "ext": ".png"}, {"name": "109277452", "path": "./pixiv/2023-06-24-14-07-56/109277452.jpg", "index": 29, "user": "\u3072\u3068\u307f\u3093", "ext": ".jpg"}, {"name": "109254352", "path": "./pixiv/2023-06-24-14-07-56/109254352.jpg", "index": 30, "user": "Criin", "ext": ".jpg"}, {"name": "109223602", "path": "./pixiv/2023-06-24-14-07-56/109223602.jpg", "index": 31, "user": "pasoputi", "ext": ".jpg"}, {"name": "109223682", "path": "./pixiv/2023-06-24-14-07-56/109223682.jpg", "index": 32, "user": "Torriet-\u30c8\u30ea\u30a8\u30c3\u30c8-", "ext": ".jpg"}, {"name": "109259477", "path": "./pixiv/2023-06-24-14-07-56/109259477.jpg", "index": 33, "user": "Toy(e)", "ext": ".jpg"}, {"name": "109252445", "path": "./pixiv/2023-06-24-14-07-56/109252445.jpg", "index": 34, "user": "\u6751\u30ab\u30eb\u30ad", "ext": ".jpg"}, {"name": "109252258", "path": "./pixiv/2023-06-24-14-07-56/109252258.jpg", "index": 35, "user": "\u9632\u4eba", "ext": ".jpg"}, {"name": "109245854", "path": "./pixiv/2023-06-24-14-07-56/109245854.png", "index": 36, "user": "\u30c1\u30e3\u30a4", "ext": ".png"}, {"name": "109263657", "path": "./pixiv/2023-06-24-14-07-56/109263657.jpg", "index": 37, "user": "8810\uff5cHayato", "ext": ".jpg"}, {"name": "109223536", "path": "./pixiv/2023-06-24-14-07-56/109223536.png", "index": 38, "user": "Lifeline", "ext": ".png"}]}