{"pixiv_pic": [{"name": "111011005", "path": "./pixiv/2023-08-22-14-09-14/111011005.png", "index": 0, "user": "\u30c1\u30e3\u30a4", "ext": ".png"}, {"name": "111020015", "path": "./pixiv/2023-08-22-14-09-14/111020015.png", "index": 1, "user": "\u304a\u304a\u307f\u3084", "ext": ".png"}, {"name": "110985975", "path": "./pixiv/2023-08-22-14-09-14/110985975.jpg", "index": 2, "user": "\u308c\u308a\u3093", "ext": ".jpg"}, {"name": "111038659", "path": "./pixiv/2023-08-22-14-09-14/111038659.png", "index": 3, "user": "Csyday", "ext": ".png"}, {"name": "110985768", "path": "./pixiv/2023-08-22-14-09-14/110985768.png", "index": 4, "user": "WERI", "ext": ".png"}, {"name": "111018786", "path": "./pixiv/2023-08-22-14-09-14/111018786.png", "index": 5, "user": "\u30dd\u30eb", "ext": ".png"}, {"name": "110986570", "path": "./pixiv/2023-08-22-14-09-14/110986570.jpg", "index": 6, "user": "\u9808\u7530\u5f69\u52a0", "ext": ".jpg"}, {"name": "111018749", "path": "./pixiv/2023-08-22-14-09-14/111018749.jpg", "index": 7, "user": "\u96e8\u58f1\u7d75\u7a79", "ext": ".jpg"}, {"name": "111018758", "path": "./pixiv/2023-08-22-14-09-14/111018758.png", "index": 8, "user": "Re\u00b0", "ext": ".png"}, {"name": "110985900", "path": "./pixiv/2023-08-22-14-09-14/110985900.jpg", "index": 9, "user": "Kinty", "ext": ".jpg"}, {"name": "110994150", "path": "./pixiv/2023-08-22-14-09-14/110994150.jpg", "index": 10, "user": "\u6f2b\u753b\u7d20\u6750\u5de5\u623f", "ext": ".jpg"}, {"name": "111032154", "path": "./pixiv/2023-08-22-14-09-14/111032154.jpg", "index": 11, "user": "\u30dd\u30c6\u30c8\u30eb\u30b9", "ext": ".jpg"}, {"name": "111001341", "path": "./pixiv/2023-08-22-14-09-14/111001341.jpg", "index": 12, "user": "8810\uff5cHayato", "ext": ".jpg"}, {"name": "111018703", "path": "./pixiv/2023-08-22-14-09-14/111018703.jpg", "index": 13, "user": "\u30b9\u30b3\u30c3\u30c6\u30a3", "ext": ".jpg"}, {"name": "111033682", "path": "./pixiv/2023-08-22-14-09-14/111033682.jpg", "index": 14, "user": "Yolanda", "ext": ".jpg"}, {"name": "111018901", "path": "./pixiv/2023-08-22-14-09-14/111018901.jpg", "index": 15, "user": "Lifeline", "ext": ".jpg"}, {"name": "111037732", "path": "./pixiv/2023-08-22-14-09-14/111037732.jpg", "index": 16, "user": "\u3088\u3046\u3058\u3064", "ext": ".jpg"}, {"name": "111003825", "path": "./pixiv/2023-08-22-14-09-14/111003825.png", "index": 17, "user": "\u9c10", "ext": ".png"}, {"name": "111009725", "path": "./pixiv/2023-08-22-14-09-14/111009725.png", "index": 18, "user": "\u9577\u702c5\u5fb9\uff20\u65e5\u66dc5\u6771\uff2535a", "ext": ".png"}, {"name": "111018706", "path": "./pixiv/2023-08-22-14-09-14/111018706.jpg", "index": 19, "user": "void_0", "ext": ".jpg"}, {"name": "111034576", "path": "./pixiv/2023-08-22-14-09-14/111034576.png", "index": 20, "user": "saihate", "ext": ".png"}, {"name": "110986440", "path": "./pixiv/2023-08-22-14-09-14/110986440.jpg", "index": 21, "user": "\u5343\u7a2e\u307f\u306e\u308a@\u304a\u4ed5\u4e8b\u52df\u96c6\u4e2d", "ext": ".jpg"}, {"name": "111000265", "path": "./pixiv/2023-08-22-14-09-14/111000265.png", "index": 22, "user": "Mika1Pikazo", "ext": ".png"}, {"name": "110992726", "path": "./pixiv/2023-08-22-14-09-14/110992726.png", "index": 23, "user": "\u3064\u306d@FANBOX\u59cb\u3081\u307e\u3057\u305f", "ext": ".png"}, {"name": "111031068", "path": "./pixiv/2023-08-22-14-09-14/111031068.jpg", "index": 24, "user": "Rafa", "ext": ".jpg"}, {"name": "111007500", "path": "./pixiv/2023-08-22-14-09-14/111007500.jpg", "index": 25, "user": "8810\uff5cHayato", "ext": ".jpg"}, {"name": "111018974", "path": "./pixiv/2023-08-22-14-09-14/111018974.jpg", "index": 26, "user": "\u304b\u3081\u307f\u305a7\u3068\u3089", "ext": ".jpg"}, {"name": "111015925", "path": "./pixiv/2023-08-22-14-09-14/111015925.png", "index": 27, "user": "\u30bf\u30ab\u30de\u30c4", "ext": ".png"}, {"name": "110985955", "path": "./pixiv/2023-08-22-14-09-14/110985955.png", "index": 28, "user": "\ud835\uddfb\ud835\uddf2\ud835\ude07\ud835\uddf6", "ext": ".png"}, {"name": "111000216", "path": "./pixiv/2023-08-22-14-09-14/111000216.jpg", "index": 29, "user": "Mika2Pikazo", "ext": ".jpg"}, {"name": "111007847", "path": "./pixiv/2023-08-22-14-09-14/111007847.jpg", "index": 30, "user": "Sa-fu", "ext": ".jpg"}, {"name": "111006453", "path": "./pixiv/2023-08-22-14-09-14/111006453.png", "index": 31, "user": "\u3053\u305f\u308d\u3046", "ext": ".png"}, {"name": "110986655", "path": "./pixiv/2023-08-22-14-09-14/110986655.jpg", "index": 32, "user": "NIAN", "ext": ".jpg"}, {"name": "110986025", "path": "./pixiv/2023-08-22-14-09-14/110986025.jpg", "index": 33, "user": "NE\u00d8N", "ext": ".jpg"}, {"name": "111033171", "path": "./pixiv/2023-08-22-14-09-14/111033171.jpg", "index": 34, "user": "Eri", "ext": ".jpg"}, {"name": "111042499", "path": "./pixiv/2023-08-22-14-09-14/111042499.jpg", "index": 35, "user": "\u304a\u3088", "ext": ".jpg"}, {"name": "110988308", "path": "./pixiv/2023-08-22-14-09-14/110988308.png", "index": 36, "user": "\uff72\uff82\uff77", "ext": ".png"}, {"name": "111014949", "path": "./pixiv/2023-08-22-14-09-14/111014949.png", "index": 37, "user": "\u9022\u7de8\u3044\u3042\u3080", "ext": ".png"}, {"name": "111027622", "path": "./pixiv/2023-08-22-14-09-14/111027622.png", "index": 38, "user": "Csyday", "ext": ".png"}, {"name": "111032406", "path": "./pixiv/2023-08-22-14-09-14/111032406.jpg", "index": 39, "user": "Mika3Pikazo", "ext": ".jpg"}, {"name": "110986308", "path": "./pixiv/2023-08-22-14-09-14/110986308.png", "index": 40, "user": "\u5343\u5343\u7d50", "ext": ".png"}, {"name": "111028938", "path": "./pixiv/2023-08-22-14-09-14/111028938.jpg", "index": 41, "user": "\u6e05\u9806(\u30c8\u30f3\u30dc\uff09\u3000", "ext": ".jpg"}, {"name": "110986067", "path": "./pixiv/2023-08-22-14-09-14/110986067.jpg", "index": 42, "user": "\u30b1\u30fc\u30b9\u30ef\u30d9\u3010K-SUWABE\u3011", "ext": ".jpg"}, {"name": "110990851", "path": "./pixiv/2023-08-22-14-09-14/110990851.png", "index": 43, "user": "\u30cf\u30df\u30bf", "ext": ".png"}, {"name": "110991426", "path": "./pixiv/2023-08-22-14-09-14/110991426.jpg", "index": 44, "user": "SP\u00b36p", "ext": ".jpg"}, {"name": "111018756", "path": "./pixiv/2023-08-22-14-09-14/111018756.jpg", "index": 45, "user": "\u3062\u3085\u3093", "ext": ".jpg"}, {"name": "111000288", "path": "./pixiv/2023-08-22-14-09-14/111000288.png", "index": 46, "user": "SP\u00b34p", "ext": ".png"}]}